quickbuild/__init__.py
quickbuild/core.py
quickbuild/exceptions.py
quickbuild/helpers.py
quickbuild/py.typed
quickbuild/adapters/__init__.py
quickbuild/adapters/aio.py
quickbuild/adapters/sync.py
quickbuild/endpoints/__init__.py
quickbuild/endpoints/agents.py
quickbuild/endpoints/audits.py
quickbuild/endpoints/authorizations.py
quickbuild/endpoints/builds.py
quickbuild/endpoints/changes.py
quickbuild/endpoints/configurations.py
quickbuild/endpoints/dashboards.py
quickbuild/endpoints/groups.py
quickbuild/endpoints/identifiers.py
quickbuild/endpoints/issues.py
quickbuild/endpoints/measurements.py
quickbuild/endpoints/memberships.py
quickbuild/endpoints/nodes.py
quickbuild/endpoints/profiles.py
quickbuild/endpoints/reports.py
quickbuild/endpoints/requests.py
quickbuild/endpoints/resources.py
quickbuild/endpoints/shares.py
quickbuild/endpoints/system.py
quickbuild/endpoints/tokens.py
quickbuild/endpoints/users.py
tests/__init__.py
tests/conftest.py
tests/test_agents.py
tests/test_audits.py
tests/test_authorizations.py
tests/test_builds.py
tests/test_changes.py
tests/test_configurations.py
tests/test_core.py
tests/test_dashboards.py
tests/test_groups.py
tests/test_helpers.py
tests/test_identifiers.py
tests/test_issues.py
tests/test_measurements.py
tests/test_memberships.py
tests/test_nodes.py
tests/test_profiles.py
tests/test_reports.py
tests/test_requests.py
tests/test_resources.py
tests/test_shares.py
tests/test_system.py
tests/test_tokens.py
tests/test_users.py
quickbuild-0.18.0.dist-info/LICENSE
quickbuild-0.18.0.dist-info/METADATA
quickbuild-0.18.0.dist-info/WHEEL
quickbuild-0.18.0.dist-info/top_level.txt
quickbuild-0.18.0.dist-info/RECORD
