Metadata-Version: 2.1
Name: quickbuild
Version: 0.18.0
Summary: Python client for PMEase QuickBuild
Home-page: https://github.com/pbelskiy/quickbuild
Download-URL: https://pypi.org/project/quickbuild
Author: Petr Belskiy
License: MIT
Keywords: PMEase,quickbuild
Classifier: Programming Language :: Python
Classifier: Programming Language :: Python :: 3
Classifier: Programming Language :: Python :: 3.7
Classifier: Programming Language :: Python :: 3.8
Classifier: Programming Language :: Python :: 3.9
Classifier: Programming Language :: Python :: 3.10
Classifier: Programming Language :: Python :: 3.11
Requires-Python: >=3.7
License-File: LICENSE
Requires-Dist: aiohttp (<4.0.0,>3.6.2)
Requires-Dist: requests (<3.0.0,>=2.24.0)
Requires-Dist: xmltodict (==0.12)
